katagames_sdk/__init__.py
katagames_sdk/example.py
katagames_sdk/katagames_engine/Injector.py
katagames_sdk/katagames_engine/Singleton.py
katagames_sdk/katagames_engine/_BaseGameState.py
katagames_sdk/katagames_engine/__init__.py
katagames_sdk/katagames_engine/__version__.py
katagames_sdk/katagames_engine/_hub.py
katagames_sdk/katagames_engine/event.py
katagames_sdk/katagames_engine/pal.py
katagames_sdk/katagames_engine/struct.py
katagames_sdk/katagames_engine/util.py
katagames_sdk/katagames_engine/caps/__init__.py
katagames_sdk/katagames_engine/caps/bioslike/KataFrameC.py
katagames_sdk/katagames_engine/caps/bioslike/KataFrameM.py
katagames_sdk/katagames_engine/caps/bioslike/KataFrameV.py
katagames_sdk/katagames_engine/caps/bioslike/MicroView.py
katagames_sdk/katagames_engine/caps/bioslike/__init__.py
katagames_sdk/katagames_engine/caps/engine_ground/StContainer.py
katagames_sdk/katagames_engine/caps/engine_ground/__init__.py
katagames_sdk/katagames_engine/caps/engine_ground/util.py
katagames_sdk/katagames_engine/caps/networking/AsyncMessagingCtrl.py
katagames_sdk/katagames_engine/caps/networking/EnvoiAsynchrone2.py
katagames_sdk/katagames_engine/caps/networking/__init__.py
katagames_sdk/katagames_engine/caps/networking/httpserver.py
katagames_sdk/katagames_engine/caps/struct/__init__.py
katagames_sdk/katagames_engine/caps/struct/matricks.py
katagames_sdk/katagames_engine/compo/__init__.py
katagames_sdk/katagames_engine/compo/gfx.py
katagames_sdk/katagames_engine/compo/modes.py
katagames_sdk/katagames_engine/compo/packed_capello_ft.py
katagames_sdk/katagames_engine/compo/vscreen.py
katagames_sdk/katagames_engine/foundation/__init__.py
katagames_sdk/katagames_engine/foundation/defs.py
katagames_sdk/katagames_engine/foundation/util.py
katagames_sdk/katagames_engine/ifaces/__init__.py
katagames_sdk/katagames_engine/ifaces/pygame.py
katagames_sdk/katagames_engine/looparts/__init__.py
katagames_sdk/katagames_engine/looparts/anim.py
katasdk-0.0.9.dist-info/LICENSE
katasdk-0.0.9.dist-info/METADATA
katasdk-0.0.9.dist-info/WHEEL
katasdk-0.0.9.dist-info/top_level.txt
katasdk-0.0.9.dist-info/RECORD
